{
    "IsActive": true,
    "IsOmniScriptEmbeddable": false,
    "Name": "textBlock",
    "OmniProcessId": {
        "Name": "AddComplaintParticipants",
        "VlocityDataPackType": "VlocityMatchingKeyObject",
        "VlocityMatchingRecordSourceKey": "OmniProcess/SPCM/AddComplaintParticipants/English",
        "VlocityRecordSObjectType": "OmniProcess"
    },
    "ParentElementId": {
        "Name": "addParticipants",
        "OmniProcessId": {
            "Name": "AddComplaintParticipants",
            "VlocityDataPackType": "VlocityMatchingKeyObject",
            "VlocityMatchingRecordSourceKey": "OmniProcess/SPCM/AddComplaintParticipants/English",
            "VlocityRecordSObjectType": "OmniProcess"
        },
        "VlocityDataPackType": "VlocityMatchingKeyObject",
        "VlocityMatchingRecordSourceKey": "OmniProcessElement/OmniProcess/SPCM/AddComplaintParticipants/English/addParticipants",
        "VlocityRecordSObjectType": "OmniProcessElement"
    },
    "ParentElementName": "addParticipants",
    "ParentElementType": "Step",
    "PropertySetConfig": {
        "HTMLTemplateId": "",
        "controlWidth": 12,
        "dataJSON": false,
        "label": "TextBlock1",
        "sanitize": false,
        "show": null,
        "text": "<p>Search to Add</p>",
        "textKey": ""
    },
    "Type": "Text Block",
    "VlocityDataPackType": "SObject",
    "VlocityRecordSObjectType": "OmniProcessElement",
    "VlocityRecordSourceKey": "OmniProcessElement/OmniProcess/SPCM/AddComplaintParticipants/English/textBlock"
}